{"items":[{"id":"V-EN-G3-0021","lang":"ru-RU","type":"typing","grade_min":3,"grade_max":3,"tags":"unit:V-EN-G3-0021","text":"Поддерживать тишину в классе"},{"id":"V-EN-G3-0022","lang":"ru-RU","type":"typing","grade_min":3,"grade_max":3,"tags":"unit:V-EN-G3-0022","text":"Смелый ученик"},{"id":"V-EN-G3-0023","lang":"ru-RU","type":"typing","grade_min":3,"grade_max":3,"tags":"unit:V-EN-G3-0023","text":"Школьный спортивный праздник"},{"id":"V-EN-G3-0024","lang":"ru-RU","type":"typing","grade_min":3,"grade_max":3,"tags":"unit:V-EN-G3-0024","text":"Проверка зрения очень важна"},{"id":"V-EN-G3-0025","lang":"ru-RU","type":"typing","grade_min":3,"grade_max":3,"tags":"unit:V-EN-G3-0025","text":"Ремонтировать парты и стулья в кабинете"},{"id":"V-EN-G3-0026","lang":"ru-RU","type":"typing","grade_min":3,"grade_max":3,"tags":"unit:V-EN-G3-0026","text":"Изучение новых слов очень ценно"},{"id":"V-EN-G3-0027","lang":"ru-RU","type":"typing","grade_min":3,"grade_max":3,"tags":"unit:V-EN-G3-0027","text":"Участвовать в волонтёрской работе в школе"},{"id":"V-EN-G3-0028","lang":"ru-RU","type":"typing","grade_min":3,"grade_max":3,"tags":"unit:V-EN-G3-0028","text":"Выступать на уроке — это проявление смелости"},{"id":"V-EN-G3-0029","lang":"ru-RU","type":"typing","grade_min":3,"grade_max":3,"tags":"unit:V-EN-G3-0029","text":"Витамины"},{"id":"V-EN-G3-0030","lang":"ru-RU","type":"typing","grade_min":3,"grade_max":3,"tags":"unit:V-EN-G3-0030","text":"Процесс изменений"},{"id":"V-EN-G3-0031","lang":"ru-RU","type":"typing","grade_min":3,"grade_max":3,"tags":"unit:V-EN-G3-0031","text":"Вакуумное состояние"},{"id":"V-EN-G3-0032","lang":"ru-RU","type":"typing","grade_min":3,"grade_max":3,"tags":"unit:V-EN-G3-0032","text":"Рост растений"},{"id":"V-EN-G3-0033","lang":"ru-RU","type":"typing","grade_min":3,"grade_max":3,"tags":"unit:V-EN-G3-0033","text":"Зрительная система"},{"id":"V-EN-G3-0034","lang":"ru-RU","type":"typing","grade_min":3,"grade_max":3,"tags":"unit:V-EN-G3-0034","text":"Извержение вулкана"},{"id":"V-EN-G3-0035","lang":"ru-RU","type":"typing","grade_min":3,"grade_max":3,"tags":"unit:V-EN-G3-0035","text":"Скорость и расстояние"},{"id":"V-EN-G3-0036","lang":"ru-RU","type":"typing","grade_min":3,"grade_max":3,"tags":"unit:V-EN-G3-0036","text":"Биологическое разнообразие"},{"id":"V-EN-G3-0037","lang":"ru-RU","type":"typing","grade_min":3,"grade_max":3,"tags":"unit:V-EN-G3-0037","text":"Поддерживать экологическое равновесие"},{"id":"V-EN-G3-0038","lang":"ru-RU","type":"typing","grade_min":3,"grade_max":3,"tags":"unit:V-EN-G3-0038","text":"Превращения веществ"},{"id":"V-EN-G3-0039","lang":"ru-RU","type":"typing","grade_min":3,"grade_max":3,"tags":"unit:V-EN-G3-0039","text":"Круговорот воды"},{"id":"V-EN-G3-0040","lang":"ru-RU","type":"typing","grade_min":3,"grade_max":3,"tags":"unit:V-EN-G3-0040","text":"Изменчивая погода"},{"id":"V-EN-G3-0041","lang":"ru-RU","type":"typing","grade_min":3,"grade_max":3,"tags":"unit:V-EN-G3-0041","text":"Зрительное восприятие"},{"id":"V-EN-G3-0042","lang":"ru-RU","type":"typing","grade_min":3,"grade_max":3,"tags":"unit:V-EN-G3-0042","text":"Извержение вулкана"},{"id":"V-EN-G3-0043","lang":"ru-RU","type":"typing","grade_min":3,"grade_max":3,"tags":"unit:V-EN-G3-0043","text":"Разнообразие организмов"},{"id":"V-EN-G3-0044","lang":"ru-RU","type":"typing","grade_min":3,"grade_max":3,"tags":"unit:V-EN-G3-0044","text":"Скорость и сила"},{"id":"V-EN-G3-0045","lang":"ru-RU","type":"typing","grade_min":3,"grade_max":3,"tags":"unit:V-EN-G3-0045","text":"Процесс круговорота воды"},{"id":"V-EN-G3-0046","lang":"ru-RU","type":"typing","grade_min":3,"grade_max":3,"tags":"unit:V-EN-G3-0046","text":"Тайны Вселенной"},{"id":"V-EN-G3-0047","lang":"ru-RU","type":"typing","grade_min":3,"grade_max":3,"tags":"unit:V-EN-G3-0047","text":"Эволюция организмов"},{"id":"V-EN-G3-0048","lang":"ru-RU","type":"typing","grade_min":3,"grade_max":3,"tags":"unit:V-EN-G3-0048","text":"Измерение скорости"},{"id":"V-EN-G3-0049","lang":"ru-RU","type":"typing","grade_min":3,"grade_max":3,"tags":"unit:V-EN-G3-0049","text":"Элементы, необходимые для поддержания жизни"},{"id":"V-EN-G3-0050","lang":"ru-RU","type":"typing","grade_min":3,"grade_max":3,"tags":"unit:V-EN-G3-0050","text":"Происхождение жизни"},{"id":"V-EN-G4-0001","lang":"ru-RU","type":"typing","grade_min":4,"grade_max":4,"tags":"unit:V-EN-G4-0001","text":"Спортсмен"},{"id":"V-EN-G4-0002","lang":"ru-RU","type":"typing","grade_min":4,"grade_max":4,"tags":"unit:V-EN-G4-0002","text":"Момент победы"},{"id":"V-EN-G4-0003","lang":"ru-RU","type":"typing","grade_min":4,"grade_max":4,"tags":"unit:V-EN-G4-0003","text":"Очень высокая скорость"},{"id":"V-EN-G4-0004","lang":"ru-RU","type":"typing","grade_min":4,"grade_max":4,"tags":"unit:V-EN-G4-0004","text":"Смелый участник"},{"id":"V-EN-G4-0005","lang":"ru-RU","type":"typing","grade_min":4,"grade_max":4,"tags":"unit:V-EN-G4-0005","text":"Площадка для соревнований"},{"id":"V-EN-G4-0006","lang":"ru-RU","type":"typing","grade_min":4,"grade_max":4,"tags":"unit:V-EN-G4-0006","text":"Поддержание физической формы"},{"id":"V-EN-G4-0007","lang":"ru-RU","type":"typing","grade_min":4,"grade_max":4,"tags":"unit:V-EN-G4-0007","text":"Богатый опыт"},{"id":"V-EN-G4-0008","lang":"ru-RU","type":"typing","grade_min":4,"grade_max":4,"tags":"unit:V-EN-G4-0008","text":"Широкий кругозор"},{"id":"V-EN-G4-0009","lang":"ru-RU","type":"typing","grade_min":4,"grade_max":4,"tags":"unit:V-EN-G4-0009","text":"Ценность спорта"},{"id":"V-EN-G4-0010","lang":"ru-RU","type":"typing","grade_min":4,"grade_max":4,"tags":"unit:V-EN-G4-0010","text":"Полный энергии"},{"id":"V-EN-G4-0011","lang":"ru-RU","type":"typing","grade_min":4,"grade_max":4,"tags":"unit:V-EN-G4-0011","text":"Победа или поражение — обычное дело в спорте"},{"id":"V-EN-G4-0012","lang":"ru-RU","type":"typing","grade_min":4,"grade_max":4,"tags":"unit:V-EN-G4-0012","text":"День спорта"},{"id":"V-EN-G4-0013","lang":"ru-RU","type":"typing","grade_min":4,"grade_max":4,"tags":"unit:V-EN-G4-0013","text":"Скорость и мастерство"},{"id":"V-EN-G4-0014","lang":"ru-RU","type":"typing","grade_min":4,"grade_max":4,"tags":"unit:V-EN-G4-0014","text":"Вызов и победа"},{"id":"V-EN-G4-0015","lang":"ru-RU","type":"typing","grade_min":4,"grade_max":4,"tags":"unit:V-EN-G4-0015","text":"Мечта спортсмена"},{"id":"V-EN-G4-0016","lang":"ru-RU","type":"typing","grade_min":4,"grade_max":4,"tags":"unit:V-EN-G4-0016","text":"Удовольствие от спорта"},{"id":"V-EN-G4-0017","lang":"ru-RU","type":"typing","grade_min":4,"grade_max":4,"tags":"unit:V-EN-G4-0017","text":"Поддержание выносливости"},{"id":"V-EN-G4-0018","lang":"ru-RU","type":"typing","grade_min":4,"grade_max":4,"tags":"unit:V-EN-G4-0018","text":"Исход соревнований"},{"id":"V-EN-G4-0019","lang":"ru-RU","type":"typing","grade_min":4,"grade_max":4,"tags":"unit:V-EN-G4-0019","text":"Ценность тренировки"},{"id":"V-EN-G4-0020","lang":"ru-RU","type":"typing","grade_min":4,"grade_max":4,"tags":"unit:V-EN-G4-0020","text":"Кругозор должен быть широким"},{"id":"V-EN-G4-0021","lang":"ru-RU","type":"typing","grade_min":4,"grade_max":4,"tags":"unit:V-EN-G4-0021","text":"медаль школьного спортивного праздника"},{"id":"V-EN-G4-0022","lang":"ru-RU","type":"typing","grade_min":4,"grade_max":4,"tags":"unit:V-EN-G4-0022","text":"картина"},{"id":"V-EN-G4-0023","lang":"ru-RU","type":"typing","grade_min":4,"grade_max":4,"tags":"unit:V-EN-G4-0023","text":"концерт"},{"id":"V-EN-G4-0024","lang":"ru-RU","type":"typing","grade_min":4,"grade_max":4,"tags":"unit:V-EN-G4-0024","text":"изобразительное искусство"},{"id":"V-EN-G4-0025","lang":"ru-RU","type":"typing","grade_min":4,"grade_max":4,"tags":"unit:V-EN-G4-0025","text":"изменяющиеся цвета"},{"id":"V-EN-G4-0026","lang":"ru-RU","type":"typing","grade_min":4,"grade_max":4,"tags":"unit:V-EN-G4-0026","text":"богатое воображение"},{"id":"V-EN-G4-0027","lang":"ru-RU","type":"typing","grade_min":4,"grade_max":4,"tags":"unit:V-EN-G4-0027","text":"визуальный эффект"},{"id":"V-EN-G4-0028","lang":"ru-RU","type":"typing","grade_min":4,"grade_max":4,"tags":"unit:V-EN-G4-0028","text":"ценность искусства"},{"id":"V-EN-G4-0029","lang":"ru-RU","type":"typing","grade_min":4,"grade_max":4,"tags":"unit:V-EN-G4-0029","text":"приёмы рисования"},{"id":"V-EN-G4-0030","lang":"ru-RU","type":"typing","grade_min":4,"grade_max":4,"tags":"unit:V-EN-G4-0030","text":"визуальное выражение"},{"id":"V-EN-G4-0031","lang":"ru-RU","type":"typing","grade_min":4,"grade_max":4,"tags":"unit:V-EN-G4-0031","text":"яркие цвета"},{"id":"V-EN-G4-0032","lang":"ru-RU","type":"typing","grade_min":4,"grade_max":4,"tags":"unit:V-EN-G4-0032","text":"художник творит с душой"},{"id":"V-EN-G4-0033","lang":"ru-RU","type":"typing","grade_min":4,"grade_max":4,"tags":"unit:V-EN-G4-0033","text":"изменяющиеся цвета"},{"id":"V-EN-G4-0034","lang":"ru-RU","type":"typing","grade_min":4,"grade_max":4,"tags":"unit:V-EN-G4-0034","text":"изящный танец"},{"id":"V-EN-G4-0035","lang":"ru-RU","type":"typing","grade_min":4,"grade_max":4,"tags":"unit:V-EN-G4-0035","text":"музыкальная мелодия"},{"id":"V-EN-G4-0036","lang":"ru-RU","type":"typing","grade_min":4,"grade_max":4,"tags":"unit:V-EN-G4-0036","text":"визуальная эстетика"},{"id":"V-EN-G4-0037","lang":"ru-RU","type":"typing","grade_min":4,"grade_max":4,"tags":"unit:V-EN-G4-0037","text":"изменчивые формы"},{"id":"V-EN-G4-0038","lang":"ru-RU","type":"typing","grade_min":4,"grade_max":4,"tags":"unit:V-EN-G4-0038","text":"сочетание ярких цветов"},{"id":"V-EN-G4-0039","lang":"ru-RU","type":"typing","grade_min":4,"grade_max":4,"tags":"unit:V-EN-G4-0039","text":"зрительное наслаждение"},{"id":"V-EN-G4-0040","lang":"ru-RU","type":"typing","grade_min":4,"grade_max":4,"tags":"unit:V-EN-G4-0040","text":"разнообразие художественных произведений"},{"id":"V-EN-G5-0001","lang":"ru-RU","type":"typing","grade_min":5,"grade_max":5,"tags":"unit:V-EN-G5-0001","text":"витамин"},{"id":"V-EN-G5-0002","lang":"ru-RU","type":"typing","grade_min":5,"grade_max":5,"tags":"unit:V-EN-G5-0002","text":"Для роста зелёных растений необходимы витамины."},{"id":"V-EN-G5-0003","lang":"ru-RU","type":"typing","grade_min":5,"grade_max":5,"tags":"unit:V-EN-G5-0003","text":"Горох имеет зелёный цвет, поскольку в нём содержатся витамины."},{"id":"V-EN-G5-0004","lang":"ru-RU","type":"typing","grade_min":5,"grade_max":5,"tags":"unit:V-EN-G5-0004","text":"Каждый организм в экосистеме играет важную роль."},{"id":"V-EN-G5-0005","lang":"ru-RU","type":"typing","grade_min":5,"grade_max":5,"tags":"unit:V-EN-G5-0005","text":"В лесу животным для выживания необходимы вода и пища."},{"id":"V-EN-G5-0006","lang":"ru-RU","type":"typing","grade_min":5,"grade_max":5,"tags":"unit:V-EN-G5-0006","text":"Растения производят пищу посредством фотосинтеза."},{"id":"V-EN-G5-0007","lang":"ru-RU","type":"typing","grade_min":5,"grade_max":5,"tags":"unit:V-EN-G5-0007","text":"Сохранение природной среды — наша ответственность."},{"id":"V-EN-G5-0008","lang":"ru-RU","type":"typing","grade_min":5,"grade_max":5,"tags":"unit:V-EN-G5-0008","text":"В горах можно увидеть множество прекрасных пейзажей."},{"id":"V-EN-G5-0009","lang":"ru-RU","type":"typing","grade_min":5,"grade_max":5,"tags":"unit:V-EN-G5-0009","text":"Сила ветра может изменить форму деревьев."},{"id":"V-EN-G5-0010","lang":"ru-RU","type":"typing","grade_min":5,"grade_max":5,"tags":"unit:V-EN-G5-0010","text":"Поддержание экологического баланса очень важно для Земли."},{"id":"V-EN-G5-0011","lang":"ru-RU","type":"typing","grade_min":5,"grade_max":5,"tags":"unit:V-EN-G5-0011","text":"В океане рыбы и растения сосуществуют."},{"id":"V-EN-G5-0012","lang":"ru-RU","type":"typing","grade_min":5,"grade_max":5,"tags":"unit:V-EN-G5-0012","text":"Растения"},{"id":"V-EN-G5-0013","lang":"ru-RU","type":"typing","grade_min":5,"grade_max":5,"tags":"unit:V-EN-G5-0013","text":"Извержение вулкана"},{"id":"V-EN-G5-0014","lang":"ru-RU","type":"typing","grade_min":5,"grade_max":5,"tags":"unit:V-EN-G5-0014","text":"Зелёные растения"},{"id":"V-EN-G5-0015","lang":"ru-RU","type":"typing","grade_min":5,"grade_max":5,"tags":"unit:V-EN-G5-0015","text":"Изменения в экосистеме"},{"id":"V-EN-G5-0016","lang":"ru-RU","type":"typing","grade_min":5,"grade_max":5,"tags":"unit:V-EN-G5-0016","text":"Сохранение природной среды"},{"id":"V-EN-G5-0017","lang":"ru-RU","type":"typing","grade_min":5,"grade_max":5,"tags":"unit:V-EN-G5-0017","text":"Биоразнообразие имеет важное значение"},{"id":"V-EN-G5-0018","lang":"ru-RU","type":"typing","grade_min":5,"grade_max":5,"tags":"unit:V-EN-G5-0018","text":"Сила ветра"},{"id":"V-EN-G5-0019","lang":"ru-RU","type":"typing","grade_min":5,"grade_max":5,"tags":"unit:V-EN-G5-0019","text":"Среда обитания диких животных"},{"id":"V-EN-G5-0020","lang":"ru-RU","type":"typing","grade_min":5,"grade_max":5,"tags":"unit:V-EN-G5-0020","text":"Поддержание экологического баланса"},{"id":"V-EN-G5-0021","lang":"ru-RU","type":"typing","grade_min":5,"grade_max":5,"tags":"unit:V-EN-G5-0021","text":"Красота природы"},{"id":"V-EN-G5-0022","lang":"ru-RU","type":"typing","grade_min":5,"grade_max":5,"tags":"unit:V-EN-G5-0022","text":"Овощи"},{"id":"V-EN-G5-0023","lang":"ru-RU","type":"typing","grade_min":5,"grade_max":5,"tags":"unit:V-EN-G5-0023","text":"Важность биоразнообразия"},{"id":"V-EN-G5-0024","lang":"ru-RU","type":"typing","grade_min":5,"grade_max":5,"tags":"unit:V-EN-G5-0024","text":"Находить красивые пейзажи в природе"},{"id":"V-EN-G6-0001","lang":"ru-RU","type":"typing","grade_min":6,"grade_max":6,"tags":"unit:V-EN-G6-0001","text":"Шторы"},{"id":"V-EN-G6-0002","lang":"ru-RU","type":"typing","grade_min":6,"grade_max":6,"tags":"unit:V-EN-G6-0002","text":"Диван"},{"id":"V-EN-G6-0003","lang":"ru-RU","type":"typing","grade_min":6,"grade_max":6,"tags":"unit:V-EN-G6-0003","text":"Поддерживать порядок"},{"id":"V-EN-G6-0004","lang":"ru-RU","type":"typing","grade_min":6,"grade_max":6,"tags":"unit:V-EN-G6-0004","text":"Очень уютный дом"},{"id":"V-EN-G6-0005","lang":"ru-RU","type":"typing","grade_min":6,"grade_max":6,"tags":"unit:V-EN-G6-0005","text":"Ароматы кухни"},{"id":"V-EN-G6-0006","lang":"ru-RU","type":"typing","grade_min":6,"grade_max":6,"tags":"unit:V-EN-G6-0006","text":"Украшать с душой"},{"id":"V-EN-G6-0007","lang":"ru-RU","type":"typing","grade_min":6,"grade_max":6,"tags":"unit:V-EN-G6-0007","text":"ценности"},{"id":"V-EN-G6-0008","lang":"ru-RU","type":"typing","grade_min":6,"grade_max":6,"tags":"unit:V-EN-G6-0008","text":"поддержание семейных отношений"},{"id":"V-EN-G6-0009","lang":"ru-RU","type":"typing","grade_min":6,"grade_max":6,"tags":"unit:V-EN-G6-0009","text":"изобразительное искусство"},{"id":"V-EN-G6-0010","lang":"ru-RU","type":"typing","grade_min":6,"grade_max":6,"tags":"unit:V-EN-G6-0010","text":"уютный дом"},{"id":"V-EN-G6-0011","lang":"ru-RU","type":"typing","grade_min":6,"grade_max":6,"tags":"unit:V-EN-G6-0011","text":"радости жизни"},{"id":"V-EN-G6-0012","lang":"ru-RU","type":"typing","grade_min":6,"grade_max":6,"tags":"unit:V-EN-G6-0012","text":"домашний декор"},{"id":"V-EN-G6-0013","lang":"ru-RU","type":"typing","grade_min":6,"grade_max":6,"tags":"unit:V-EN-G6-0013","text":"телевизор"},{"id":"V-EN-G6-0014","lang":"ru-RU","type":"typing","grade_min":6,"grade_max":6,"tags":"unit:V-EN-G6-0014","text":"тщательно поддерживать"},{"id":"V-EN-G6-0015","lang":"ru-RU","type":"typing","grade_min":6,"grade_max":6,"tags":"unit:V-EN-G6-0015","text":"кухонная утварь"},{"id":"V-EN-G6-0016","lang":"ru-RU","type":"typing","grade_min":6,"grade_max":6,"tags":"unit:V-EN-G6-0016","text":"комфортная обстановка"},{"id":"V-EN-G6-0017","lang":"ru-RU","type":"typing","grade_min":6,"grade_max":6,"tags":"unit:V-EN-G6-0017","text":"ценностные представления"},{"id":"V-EN-G6-0018","lang":"ru-RU","type":"typing","grade_min":6,"grade_max":6,"tags":"unit:V-EN-G6-0018","text":"бытовые удобства"},{"id":"V-EN-G6-0019","lang":"ru-RU","type":"typing","grade_min":6,"grade_max":6,"tags":"unit:V-EN-G6-0019","text":"ремонтные услуги"},{"id":"V-EN-G6-0020","lang":"ru-RU","type":"typing","grade_min":6,"grade_max":6,"tags":"unit:V-EN-G6-0020","text":"кухня"},{"id":"V-EN-G6-0021","lang":"ru-RU","type":"typing","grade_min":6,"grade_max":6,"tags":"unit:V-EN-G6-0021","text":"ванная комната"},{"id":"V-EN-G6-0022","lang":"ru-RU","type":"typing","grade_min":6,"grade_max":6,"tags":"unit:V-EN-G6-0022","text":"поддерживать домашний очаг"},{"id":"V-EN-G6-0023","lang":"ru-RU","type":"typing","grade_min":6,"grade_max":6,"tags":"unit:V-EN-G6-0023","text":"ценность"},{"id":"V-EN-G6-0024","lang":"ru-RU","type":"typing","grade_min":6,"grade_max":6,"tags":"unit:V-EN-G6-0024","text":"насыщенные цвета"},{"id":"V-EN-G6-0025","lang":"ru-RU","type":"typing","grade_min":6,"grade_max":6,"tags":"unit:V-EN-G6-0025","text":"широкое поле зрения"},{"id":"W-EN-G1-0001","lang":"ru-RU","type":"typing","grade_min":1,"grade_max":1,"tags":"unit:W-EN-G1-0001","text":"водная кисточка"},{"id":"W-EN-G1-0002","lang":"ru-RU","type":"typing","grade_min":1,"grade_max":1,"tags":"unit:W-EN-G1-0002","text":"белая доска"},{"id":"W-EN-G1-0003","lang":"ru-RU","type":"typing","grade_min":1,"grade_max":1,"tags":"unit:W-EN-G1-0003","text":"ранец"},{"id":"W-EN-G1-0004","lang":"ru-RU","type":"typing","grade_min":1,"grade_max":1,"tags":"unit:W-EN-G1-0004","text":"Мы учимся вместе"},{"id":"W-EN-G1-0005","lang":"ru-RU","type":"typing","grade_min":1,"grade_max":1,"tags":"unit:W-EN-G1-0005","text":"веселый урок"},{"id":"W-EN-G1-0006","lang":"ru-RU","type":"typing","grade_min":1,"grade_max":1,"tags":"unit:W-EN-G1-0006","text":"Что в пенале?"},{"id":"W-EN-G1-0007","lang":"ru-RU","type":"typing","grade_min":1,"grade_max":1,"tags":"unit:W-EN-G1-0007","text":"Я люблю писать"},{"id":"W-EN-G1-0008","lang":"ru-RU","type":"typing","grade_min":1,"grade_max":1,"tags":"unit:W-EN-G1-0008","text":"Чтобы лучше учиться"},{"id":"W-EN-G1-0009","lang":"ru-RU","type":"typing","grade_min":1,"grade_max":1,"tags":"unit:W-EN-G1-0009","text":"Мой друг в школе"},{"id":"W-EN-G1-0010","lang":"ru-RU","type":"typing","grade_min":1,"grade_max":1,"tags":"unit:W-EN-G1-0010","text":"Я умею рисовать и писать"},{"id":"W-EN-G1-0011","lang":"ru-RU","type":"typing","grade_min":1,"grade_max":1,"tags":"unit:W-EN-G1-0011","text":"Игрушки в классе"},{"id":"W-EN-G1-0012","lang":"ru-RU","type":"typing","grade_min":1,"grade_max":1,"tags":"unit:W-EN-G1-0012","text":"Пенал"},{"id":"W-EN-G1-0013","lang":"ru-RU","type":"typing","grade_min":1,"grade_max":1,"tags":"unit:W-EN-G1-0013","text":"Я люблю школу"},{"id":"W-EN-G1-0014","lang":"ru-RU","type":"typing","grade_min":1,"grade_max":1,"tags":"unit:W-EN-G1-0014","text":"Писать очень интересно"},{"id":"W-EN-G1-0015","lang":"ru-RU","type":"typing","grade_min":1,"grade_max":1,"tags":"unit:W-EN-G1-0015","text":"У меня много книг"},{"id":"W-EN-G1-0016","lang":"ru-RU","type":"typing","grade_min":1,"grade_max":1,"tags":"unit:W-EN-G1-0016","text":"Зачем ходить в школу"},{"id":"W-EN-G1-0017","lang":"ru-RU","type":"typing","grade_min":1,"grade_max":1,"tags":"unit:W-EN-G1-0017","text":"Я умею рисовать"},{"id":"W-EN-G1-0018","lang":"ru-RU","type":"typing","grade_min":1,"grade_max":1,"tags":"unit:W-EN-G1-0018","text":"Тёплое солнце"},{"id":"W-EN-G1-0019","lang":"ru-RU","type":"typing","grade_min":1,"grade_max":1,"tags":"unit:W-EN-G1-0019","text":"Когда пишешь, нужно сосредоточиться"},{"id":"W-EN-G1-0020","lang":"ru-RU","type":"typing","grade_min":1,"grade_max":1,"tags":"unit:W-EN-G1-0020","text":"Чтобы стать лучше, мы стараемся"},{"id":"W-EN-G1-0021","lang":"ru-RU","type":"typing","grade_min":1,"grade_max":1,"tags":"unit:W-EN-G1-0021","text":"Я люблю рисовать и писать"},{"id":"W-EN-G1-0022","lang":"ru-RU","type":"typing","grade_min":1,"grade_max":1,"tags":"unit:W-EN-G1-0022","text":"Игрушки в классе очень забавные"},{"id":"W-EN-G1-0023","lang":"ru-RU","type":"typing","grade_min":1,"grade_max":1,"tags":"unit:W-EN-G1-0023","text":"Тёплый солнечный свет проникает в класс"},{"id":"W-EN-G1-0024","lang":"ru-RU","type":"typing","grade_min":1,"grade_max":1,"tags":"unit:W-EN-G1-0024","text":"В пенале много канцелярских принадлежностей"},{"id":"W-EN-G1-0025","lang":"ru-RU","type":"typing","grade_min":1,"grade_max":1,"tags":"unit:W-EN-G1-0025","text":"Вода"},{"id":"W-EN-G1-0026","lang":"ru-RU","type":"typing","grade_min":1,"grade_max":1,"tags":"unit:W-EN-G1-0026","text":"Ветер"},{"id":"W-EN-G1-0027","lang":"ru-RU","type":"typing","grade_min":1,"grade_max":1,"tags":"unit:W-EN-G1-0027","text":"Температура"},{"id":"W-EN-G1-0028","lang":"ru-RU","type":"typing","grade_min":1,"grade_max":1,"tags":"unit:W-EN-G1-0028","text":"Растениям для роста нужна влага"},{"id":"W-EN-G1-0029","lang":"ru-RU","type":"typing","grade_min":1,"grade_max":1,"tags":"unit:W-EN-G1-0029","text":"Дикие животные"},{"id":"W-EN-G1-0030","lang":"ru-RU","type":"typing","grade_min":1,"grade_max":1,"tags":"unit:W-EN-G1-0030","text":"Вода — источник жизни"},{"id":"W-EN-G1-0031","lang":"ru-RU","type":"typing","grade_min":1,"grade_max":1,"tags":"unit:W-EN-G1-0031","text":"Тёплый солнечный свет помогает растениям расти"},{"id":"W-EN-G1-0032","lang":"ru-RU","type":"typing","grade_min":1,"grade_max":1,"tags":"unit:W-EN-G1-0032","text":"круговорот воды в природе"},{"id":"W-EN-G1-0033","lang":"ru-RU","type":"typing","grade_min":1,"grade_max":1,"tags":"unit:W-EN-G1-0033","text":"ветровая энергия является возобновляемым источником энергии"},{"id":"W-EN-G1-0034","lang":"ru-RU","type":"typing","grade_min":1,"grade_max":1,"tags":"unit:W-EN-G1-0034","text":"водяной пар при испарении образует облака"},{"id":"W-EN-G1-0035","lang":"ru-RU","type":"typing","grade_min":1,"grade_max":1,"tags":"unit:W-EN-G1-0035","text":"парниковый эффект влияет на климат"},{"id":"W-EN-G1-0036","lang":"ru-RU","type":"typing","grade_min":1,"grade_max":1,"tags":"unit:W-EN-G1-0036","text":"белые облака плывут по небу"},{"id":"W-EN-G1-0037","lang":"ru-RU","type":"typing","grade_min":1,"grade_max":1,"tags":"unit:W-EN-G1-0037","text":"растения"},{"id":"W-EN-G1-0038","lang":"ru-RU","type":"typing","grade_min":1,"grade_max":1,"tags":"unit:W-EN-G1-0038","text":"тёплые солнечные лучи"},{"id":"W-EN-G1-0039","lang":"ru-RU","type":"typing","grade_min":1,"grade_max":1,"tags":"unit:W-EN-G1-0039","text":"сила ветра может приводить в движение лодки"},{"id":"W-EN-G1-0040","lang":"ru-RU","type":"typing","grade_min":1,"grade_max":1,"tags":"unit:W-EN-G1-0040","text":"микроорганизмы живут в воде"},{"id":"W-EN-G1-0041","lang":"ru-RU","type":"typing","grade_min":1,"grade_max":1,"tags":"unit:W-EN-G1-0041","text":"температура влияет на состояние воды"},{"id":"W-EN-G1-0042","lang":"ru-RU","type":"typing","grade_min":1,"grade_max":1,"tags":"unit:W-EN-G1-0042","text":"белые облака в небе"},{"id":"W-EN-G1-0043","lang":"ru-RU","type":"typing","grade_min":1,"grade_max":1,"tags":"unit:W-EN-G1-0043","text":"растения нуждаются в воде"},{"id":"W-EN-G1-0044","lang":"ru-RU","type":"typing","grade_min":1,"grade_max":1,"tags":"unit:W-EN-G1-0044","text":"на небе много звёзд"},{"id":"W-EN-G1-0045","lang":"ru-RU","type":"typing","grade_min":1,"grade_max":1,"tags":"unit:W-EN-G1-0045","text":"сила ветра"},{"id":"W-EN-G1-0046","lang":"ru-RU","type":"typing","grade_min":1,"grade_max":1,"tags":"unit:W-EN-G1-0046","text":"изменения температуры"},{"id":"W-EN-G2-0001","lang":"ru-RU","type":"typing","grade_min":2,"grade_max":2,"tags":"unit:W-EN-G2-0001","text":"школьный спортивный праздник"},{"id":"W-EN-G2-0002","lang":"ru-RU","type":"typing","grade_min":2,"grade_max":2,"tags":"unit:W-EN-G2-0002","text":"катание на лыжах"},{"id":"W-EN-G2-0003","lang":"ru-RU","type":"typing","grade_min":2,"grade_max":2,"tags":"unit:W-EN-G2-0003","text":"футбольный матч"},{"id":"W-EN-G2-0004","lang":"ru-RU","type":"typing","grade_min":2,"grade_max":2,"tags":"unit:W-EN-G2-0004","text":"на теннисном корте"},{"id":"W-EN-G2-0005","lang":"ru-RU","type":"typing","grade_min":2,"grade_max":2,"tags":"unit:W-EN-G2-0005","text":"выиграть матч"},{"id":"W-EN-G2-0006","lang":"ru-RU","type":"typing","grade_min":2,"grade_max":2,"tags":"unit:W-EN-G2-0006","text":"дух спортсмена"},{"id":"W-EN-G2-0007","lang":"ru-RU","type":"typing","grade_min":2,"grade_max":2,"tags":"unit:W-EN-G2-0007","text":"водные виды спорта"},{"id":"W-EN-G2-0008","lang":"ru-RU","type":"typing","grade_min":2,"grade_max":2,"tags":"unit:W-EN-G2-0008","text":"хорошо проводить время"},{"id":"W-EN-G2-0009","lang":"ru-RU","type":"typing","grade_min":2,"grade_max":2,"tags":"unit:W-EN-G2-0009","text":"мне нравится играть в футбол"},{"id":"W-EN-G2-0010","lang":"ru-RU","type":"typing","grade_min":2,"grade_max":2,"tags":"unit:W-EN-G2-0010","text":"стремиться к победе"},{"id":"W-EN-G2-0011","lang":"ru-RU","type":"typing","grade_min":2,"grade_max":2,"tags":"unit:W-EN-G2-0011","text":"Спорт — залог здорового образа жизни"},{"id":"W-EN-G2-0012","lang":"ru-RU","type":"typing","grade_min":2,"grade_max":2,"tags":"unit:W-EN-G2-0012","text":"спортсмен"},{"id":"W-EN-G2-0013","lang":"ru-RU","type":"typing","grade_min":2,"grade_max":2,"tags":"unit:W-EN-G2-0013","text":"когда играешь в футбол"},{"id":"W-EN-G2-0014","lang":"ru-RU","type":"typing","grade_min":2,"grade_max":2,"tags":"unit:W-EN-G2-0014","text":"катание на лыжах доставляет море удовольствия"},{"id":"W-EN-G2-0015","lang":"ru-RU","type":"typing","grade_min":2,"grade_max":2,"tags":"unit:W-EN-G2-0015","text":"баскетбольный матч"},{"id":"W-EN-G2-0016","lang":"ru-RU","type":"typing","grade_min":2,"grade_max":2,"tags":"unit:W-EN-G2-0016","text":"мне нравится плавать"},{"id":"W-EN-G2-0017","lang":"ru-RU","type":"typing","grade_min":2,"grade_max":2,"tags":"unit:W-EN-G2-0017","text":"на школьном Дне здоровья всегда весело и многолюдно"},{"id":"W-EN-G2-0018","lang":"ru-RU","type":"typing","grade_min":2,"grade_max":2,"tags":"unit:W-EN-G2-0018","text":"я выиграю"},{"id":"W-EN-G2-0019","lang":"ru-RU","type":"typing","grade_min":2,"grade_max":2,"tags":"unit:W-EN-G2-0019","text":"спорт"},{"id":"W-EN-G2-0020","lang":"ru-RU","type":"typing","grade_min":2,"grade_max":2,"tags":"unit:W-EN-G2-0020","text":"футбол"},{"id":"W-EN-G2-0021","lang":"ru-RU","type":"typing","grade_min":2,"grade_max":2,"tags":"unit:W-EN-G2-0021","text":"плавание"},{"id":"W-EN-G2-0022","lang":"ru-RU","type":"typing","grade_min":2,"grade_max":2,"tags":"unit:W-EN-G2-0022","text":"баскетбол"},{"id":"W-EN-G2-0023","lang":"ru-RU","type":"typing","grade_min":2,"grade_max":2,"tags":"unit:W-EN-G2-0023","text":"школьный спортивный праздник — это очень интересно"},{"id":"W-EN-G2-0024","lang":"ru-RU","type":"typing","grade_min":2,"grade_max":2,"tags":"unit:W-EN-G2-0024","text":"мне нравится заниматься спортом"},{"id":"W-EN-G2-0025","lang":"ru-RU","type":"typing","grade_min":2,"grade_max":2,"tags":"unit:W-EN-G2-0025","text":"весёлое время, проведённое за спортом"},{"id":"W-EN-G2-0026","lang":"ru-RU","type":"typing","grade_min":2,"grade_max":2,"tags":"unit:W-EN-G2-0026","text":"давай вместе позанимаемся спортом"},{"id":"W-EN-G2-0027","lang":"ru-RU","type":"typing","grade_min":2,"grade_max":2,"tags":"unit:W-EN-G2-0027","text":"спорт укрепляет моё здоровье"},{"id":"W-EN-G2-0028","lang":"ru-RU","type":"typing","grade_min":2,"grade_max":2,"tags":"unit:W-EN-G2-0028","text":"рисовать"},{"id":"W-EN-G2-0029","lang":"ru-RU","type":"typing","grade_min":2,"grade_max":2,"tags":"unit:W-EN-G2-0029","text":"картинная галерея"},{"id":"W-EN-G2-0030","lang":"ru-RU","type":"typing","grade_min":2,"grade_max":2,"tags":"unit:W-EN-G2-0030","text":"акварельная живопись"},{"id":"W-EN-G2-0031","lang":"ru-RU","type":"typing","grade_min":2,"grade_max":2,"tags":"unit:W-EN-G2-0031","text":"художник"},{"id":"W-EN-G2-0032","lang":"ru-RU","type":"typing","grade_min":2,"grade_max":2,"tags":"unit:W-EN-G2-0032","text":"принадлежности для рисования"},{"id":"W-EN-G2-0033","lang":"ru-RU","type":"typing","grade_min":2,"grade_max":2,"tags":"unit:W-EN-G2-0033","text":"рисовать акварелью"},{"id":"W-EN-G2-0034","lang":"ru-RU","type":"typing","grade_min":2,"grade_max":2,"tags":"unit:W-EN-G2-0034","text":"цвета на холсте"},{"id":"W-EN-G2-0035","lang":"ru-RU","type":"typing","grade_min":2,"grade_max":2,"tags":"unit:W-EN-G2-0035","text":"стиль произведения искусства"},{"id":"W-EN-G2-0036","lang":"ru-RU","type":"typing","grade_min":2,"grade_max":2,"tags":"unit:W-EN-G2-0036","text":"Передайте эмоции с помощью цвета."},{"id":"W-EN-G2-0037","lang":"ru-RU","type":"typing","grade_min":2,"grade_max":2,"tags":"unit:W-EN-G2-0037","text":"Нарисуйте мир своей мечты."},{"id":"W-EN-G2-0038","lang":"ru-RU","type":"typing","grade_min":2,"grade_max":2,"tags":"unit:W-EN-G2-0038","text":"Искусство приносит нам радость."},{"id":"W-EN-G2-0039","lang":"ru-RU","type":"typing","grade_min":2,"grade_max":2,"tags":"unit:W-EN-G2-0039","text":"Творческая мастерская."},{"id":"W-EN-G2-0040","lang":"ru-RU","type":"typing","grade_min":2,"grade_max":2,"tags":"unit:W-EN-G2-0040","text":"Произведение искусства."},{"id":"W-EN-G2-0041","lang":"ru-RU","type":"typing","grade_min":2,"grade_max":2,"tags":"unit:W-EN-G2-0041","text":"Выражайте с помощью цвета."},{"id":"W-EN-G2-0042","lang":"ru-RU","type":"typing","grade_min":2,"grade_max":2,"tags":"unit:W-EN-G2-0042","text":"Кисти и краски."},{"id":"W-EN-G2-0043","lang":"ru-RU","type":"typing","grade_min":2,"grade_max":2,"tags":"unit:W-EN-G2-0043","text":"Творчество художника."},{"id":"W-EN-G2-0044","lang":"ru-RU","type":"typing","grade_min":2,"grade_max":2,"tags":"unit:W-EN-G2-0044","text":"Создавайте от души."},{"id":"W-EN-G2-0045","lang":"ru-RU","type":"typing","grade_min":2,"grade_max":2,"tags":"unit:W-EN-G2-0045","text":"Удовольствие от рисования."},{"id":"W-EN-G2-0046","lang":"ru-RU","type":"typing","grade_min":2,"grade_max":2,"tags":"unit:W-EN-G2-0046","text":"Искусство делает нас счастливыми."},{"id":"W-EN-G2-0047","lang":"ru-RU","type":"typing","grade_min":2,"grade_max":2,"tags":"unit:W-EN-G2-0047","text":"Теплые цвета."},{"id":"W-EN-G2-0048","lang":"ru-RU","type":"typing","grade_min":2,"grade_max":2,"tags":"unit:W-EN-G2-0048","text":"Произведения в художественном музее."},{"id":"W-EN-G2-0049","lang":"ru-RU","type":"typing","grade_min":2,"grade_max":2,"tags":"unit:W-EN-G2-0049","text":"Весёлая музыка."},{"id":"W-EN-G2-0050","lang":"ru-RU","type":"typing","grade_min":2,"grade_max":2,"tags":"unit:W-EN-G2-0050","text":"Техники рисования с натуры."},{"id":"W-EN-G2-0051","lang":"ru-RU","type":"typing","grade_min":2,"grade_max":2,"tags":"unit:W-EN-G2-0051","text":"Мир искусства."},{"id":"W-EN-G2-0052","lang":"ru-RU","type":"typing","grade_min":2,"grade_max":2,"tags":"unit:W-EN-G2-0052","text":"Мечта художника."},{"id":"W-EN-G2-0053","lang":"ru-RU","type":"typing","grade_min":2,"grade_max":2,"tags":"unit:W-EN-G2-0053","text":"Процесс творчества."},{"id":"W-EN-G2-0054","lang":"ru-RU","type":"typing","grade_min":2,"grade_max":2,"tags":"unit:W-EN-G2-0054","text":"Очарование произведений искусства."},{"id":"W-EN-G2-0055","lang":"ru-RU","type":"typing","grade_min":2,"grade_max":2,"tags":"unit:W-EN-G2-0055","text":"Творите от всей души."},{"id":"W-EN-G3-0001","lang":"ru-RU","type":"typing","grade_min":3,"grade_max":3,"tags":"unit:W-EN-G3-0001","text":"Вода."},{"id":"W-EN-G3-0002","lang":"ru-RU","type":"typing","grade_min":3,"grade_max":3,"tags":"unit:W-EN-G3-0002","text":"Ветер."},{"id":"W-EN-G3-0003","lang":"ru-RU","type":"typing","grade_min":3,"grade_max":3,"tags":"unit:W-EN-G3-0003","text":"Дикие животные."},{"id":"W-EN-G3-0004","lang":"ru-RU","type":"typing","grade_min":3,"grade_max":3,"tags":"unit:W-EN-G3-0004","text":"В лесу деревья колышутся на ветру."},{"id":"W-EN-G3-0005","lang":"ru-RU","type":"typing","grade_min":3,"grade_max":3,"tags":"unit:W-EN-G3-0005","text":"Тёплые лучи солнца."},{"id":"W-EN-G3-0006","lang":"ru-RU","type":"typing","grade_min":3,"grade_max":3,"tags":"unit:W-EN-G3-0006","text":"Шелест текущей воды"},{"id":"W-EN-G3-0007","lang":"ru-RU","type":"typing","grade_min":3,"grade_max":3,"tags":"unit:W-EN-G3-0007","text":"У озера парят белые цапли"},{"id":"W-EN-G3-0008","lang":"ru-RU","type":"typing","grade_min":3,"grade_max":3,"tags":"unit:W-EN-G3-0008","text":"Звук ветра"},{"id":"W-EN-G3-0009","lang":"ru-RU","type":"typing","grade_min":3,"grade_max":3,"tags":"unit:W-EN-G3-0009","text":"Пышное цветение полевых цветов"},{"id":"W-EN-G3-0010","lang":"ru-RU","type":"typing","grade_min":3,"grade_max":3,"tags":"unit:W-EN-G3-0010","text":"В горах проплывают облака"},{"id":"W-EN-G3-0011","lang":"ru-RU","type":"typing","grade_min":3,"grade_max":3,"tags":"unit:W-EN-G3-0011","text":"Нежный ветер ласково дует"},{"id":"W-EN-G3-0012","lang":"ru-RU","type":"typing","grade_min":3,"grade_max":3,"tags":"unit:W-EN-G3-0012","text":"Плывущие белые облака"},{"id":"W-EN-G3-0013","lang":"ru-RU","type":"typing","grade_min":3,"grade_max":3,"tags":"unit:W-EN-G3-0013","text":"Растут деревья"},{"id":"W-EN-G3-0014","lang":"ru-RU","type":"typing","grade_min":3,"grade_max":3,"tags":"unit:W-EN-G3-0014","text":"Рыбы в воде"},{"id":"W-EN-G3-0015","lang":"ru-RU","type":"typing","grade_min":3,"grade_max":3,"tags":"unit:W-EN-G3-0015","text":"Легкий ветерок"},{"id":"W-EN-G3-0016","lang":"ru-RU","type":"typing","grade_min":3,"grade_max":3,"tags":"unit:W-EN-G3-0016","text":"Стрекозы порхают"},{"id":"W-EN-G3-0017","lang":"ru-RU","type":"typing","grade_min":3,"grade_max":3,"tags":"unit:W-EN-G3-0017","text":"Красота мира"},{"id":"W-EN-G3-0018","lang":"ru-RU","type":"typing","grade_min":3,"grade_max":3,"tags":"unit:W-EN-G3-0018","text":"Облака"},{"id":"W-EN-G3-0019","lang":"ru-RU","type":"typing","grade_min":3,"grade_max":3,"tags":"unit:W-EN-G3-0019","text":"Зеленые деревья"},{"id":"W-EN-G3-0020","lang":"ru-RU","type":"typing","grade_min":3,"grade_max":3,"tags":"unit:W-EN-G3-0020","text":"Круговорот воды"},{"id":"W-EN-G3-0021","lang":"ru-RU","type":"typing","grade_min":3,"grade_max":3,"tags":"unit:W-EN-G3-0021","text":"Стрекозы летают"},{"id":"W-EN-G4-0001","lang":"ru-RU","type":"typing","grade_min":4,"grade_max":4,"tags":"unit:W-EN-G4-0001","text":"Окно"},{"id":"W-EN-G4-0002","lang":"ru-RU","type":"typing","grade_min":4,"grade_max":4,"tags":"unit:W-EN-G4-0002","text":"Теплый дом"},{"id":"W-EN-G4-0003","lang":"ru-RU","type":"typing","grade_min":4,"grade_max":4,"tags":"unit:W-EN-G4-0003","text":"Стиральная машина"},{"id":"W-EN-G4-0004","lang":"ru-RU","type":"typing","grade_min":4,"grade_max":4,"tags":"unit:W-EN-G4-0004","text":"Добро пожаловать домой"},{"id":"W-EN-G4-0005","lang":"ru-RU","type":"typing","grade_min":4,"grade_max":4,"tags":"unit:W-EN-G4-0005","text":"Картина на стене"},{"id":"W-EN-G4-0006","lang":"ru-RU","type":"typing","grade_min":4,"grade_max":4,"tags":"unit:W-EN-G4-0006","text":"Ящик с игрушками"},{"id":"W-EN-G4-0007","lang":"ru-RU","type":"typing","grade_min":4,"grade_max":4,"tags":"unit:W-EN-G4-0007","text":"Цвет штор"},{"id":"W-EN-G4-0008","lang":"ru-RU","type":"typing","grade_min":4,"grade_max":4,"tags":"unit:W-EN-G4-0008","text":"Аромат кухни"},{"id":"W-EN-G4-0009","lang":"ru-RU","type":"typing","grade_min":4,"grade_max":4,"tags":"unit:W-EN-G4-0009","text":"Чистота в ванной"},{"id":"W-EN-G4-0010","lang":"ru-RU","type":"typing","grade_min":4,"grade_max":4,"tags":"unit:W-EN-G4-0010","text":"Радость семейного торжества"},{"id":"W-EN-G4-0011","lang":"ru-RU","type":"typing","grade_min":4,"grade_max":4,"tags":"unit:W-EN-G4-0011","text":"Тёплое освещение"},{"id":"W-EN-G4-0012","lang":"ru-RU","type":"typing","grade_min":4,"grade_max":4,"tags":"unit:W-EN-G4-0012","text":"Наша кухня очень большая"},{"id":"W-EN-G4-0013","lang":"ru-RU","type":"typing","grade_min":4,"grade_max":4,"tags":"unit:W-EN-G4-0013","text":"Ванная комната"},{"id":"W-EN-G4-0014","lang":"ru-RU","type":"typing","grade_min":4,"grade_max":4,"tags":"unit:W-EN-G4-0014","text":"Мне нравится моя комната"},{"id":"W-EN-G4-0015","lang":"ru-RU","type":"typing","grade_min":4,"grade_max":4,"tags":"unit:W-EN-G4-0015","text":"Уютное семейное торжество"},{"id":"W-EN-G4-0016","lang":"ru-RU","type":"typing","grade_min":4,"grade_max":4,"tags":"unit:W-EN-G4-0016","text":"Готовить ужин для семьи"},{"id":"W-EN-G4-0017","lang":"ru-RU","type":"typing","grade_min":4,"grade_max":4,"tags":"unit:W-EN-G4-0017","text":"Наша кухня"},{"id":"W-EN-G4-0018","lang":"ru-RU","type":"typing","grade_min":4,"grade_max":4,"tags":"unit:W-EN-G4-0018","text":"Готовить еду для семьи"},{"id":"W-EN-G4-0019","lang":"ru-RU","type":"typing","grade_min":4,"grade_max":4,"tags":"unit:W-EN-G4-0019","text":"Птицы на крыше"},{"id":"W-EN-G5-0001","lang":"ru-RU","type":"typing","grade_min":5,"grade_max":5,"tags":"unit:W-EN-G5-0001","text":"Волк"},{"id":"W-EN-G5-0002","lang":"ru-RU","type":"typing","grade_min":5,"grade_max":5,"tags":"unit:W-EN-G5-0002","text":"Дельфины плавают в воде."},{"id":"W-EN-G5-0003","lang":"ru-RU","type":"typing","grade_min":5,"grade_max":5,"tags":"unit:W-EN-G5-0003","text":"Ящерица"},{"id":"W-EN-G5-0004","lang":"ru-RU","type":"typing","grade_min":5,"grade_max":5,"tags":"unit:W-EN-G5-0004","text":"Львы охотятся на саванне."},{"id":"W-EN-G5-0005","lang":"ru-RU","type":"typing","grade_min":5,"grade_max":5,"tags":"unit:W-EN-G5-0005","text":"Кит — самое большое морское животное."},{"id":"W-EN-G5-0006","lang":"ru-RU","type":"typing","grade_min":5,"grade_max":5,"tags":"unit:W-EN-G5-0006","text":"Черепаха"},{"id":"W-EN-G5-0007","lang":"ru-RU","type":"typing","grade_min":5,"grade_max":5,"tags":"unit:W-EN-G5-0007","text":"Стая волков охотится вместе."},{"id":"W-EN-G5-0008","lang":"ru-RU","type":"typing","grade_min":5,"grade_max":5,"tags":"unit:W-EN-G5-0008","text":"Выдры резвятся в реке."},{"id":"W-EN-G5-0009","lang":"ru-RU","type":"typing","grade_min":5,"grade_max":5,"tags":"unit:W-EN-G5-0009","text":"Кабан"},{"id":"W-EN-G5-0010","lang":"ru-RU","type":"typing","grade_min":5,"grade_max":5,"tags":"unit:W-EN-G5-0010","text":"Совы активны ночью."},{"id":"W-EN-G5-0011","lang":"ru-RU","type":"typing","grade_min":5,"grade_max":5,"tags":"unit:W-EN-G5-0011","text":"Птички поют на дереве."},{"id":"W-EN-G5-0012","lang":"ru-RU","type":"typing","grade_min":5,"grade_max":5,"tags":"unit:W-EN-G5-0012","text":"Дикие животные"},{"id":"W-EN-G5-0013","lang":"ru-RU","type":"typing","grade_min":5,"grade_max":5,"tags":"unit:W-EN-G5-0013","text":"Кит — самое крупное млекопитающее."},{"id":"W-EN-G5-0014","lang":"ru-RU","type":"typing","grade_min":5,"grade_max":5,"tags":"unit:W-EN-G5-0014","text":"Улитки живут во влажных местах."},{"id":"W-EN-G5-0015","lang":"ru-RU","type":"typing","grade_min":5,"grade_max":5,"tags":"unit:W-EN-G5-0015","text":"Выдры резвятся в воде."},{"id":"W-EN-G5-0016","lang":"ru-RU","type":"typing","grade_min":5,"grade_max":5,"tags":"unit:W-EN-G5-0016","text":"Белуха"},{"id":"W-EN-G5-0017","lang":"ru-RU","type":"typing","grade_min":5,"grade_max":5,"tags":"unit:W-EN-G5-0017","text":"Заповедник дикой природы"},{"id":"W-EN-G5-0018","lang":"ru-RU","type":"typing","grade_min":5,"grade_max":5,"tags":"unit:W-EN-G5-0018","text":"Стрекоза порхает у воды."},{"id":"W-EN-G5-0019","lang":"ru-RU","type":"typing","grade_min":5,"grade_max":5,"tags":"unit:W-EN-G5-0019","text":"Ящерица греется на солнце."},{"id":"W-EN-G5-0020","lang":"ru-RU","type":"typing","grade_min":5,"grade_max":5,"tags":"unit:W-EN-G5-0020","text":"Выдра любит играть в воде."},{"id":"W-EN-G5-0021","lang":"ru-RU","type":"typing","grade_min":5,"grade_max":5,"tags":"unit:W-EN-G5-0021","text":"Кабан живёт в лесу."},{"id":"W-EN-G5-0022","lang":"ru-RU","type":"typing","grade_min":5,"grade_max":5,"tags":"unit:W-EN-G5-0022","text":"Орёл парит в небе."},{"id":"W-EN-G5-0023","lang":"ru-RU","type":"typing","grade_min":5,"grade_max":5,"tags":"unit:W-EN-G5-0023","text":"Улитка ползёт во влажном месте."},{"id":"W-EN-G5-0024","lang":"ru-RU","type":"typing","grade_min":5,"grade_max":5,"tags":"unit:W-EN-G5-0024","text":"Вой волка раздаётся ночью."},{"id":"W-EN-G5-0025","lang":"ru-RU","type":"typing","grade_min":5,"grade_max":5,"tags":"unit:W-EN-G5-0025","text":"Дружное сообщество"},{"id":"W-EN-G5-0026","lang":"ru-RU","type":"typing","grade_min":5,"grade_max":5,"tags":"unit:W-EN-G5-0026","text":"Добро пожаловать в наше сообщество"},{"id":"W-EN-G5-0027","lang":"ru-RU","type":"typing","grade_min":5,"grade_max":5,"tags":"unit:W-EN-G5-0027","text":"Работа — часть командного сотрудничества"},{"id":"W-EN-G5-0028","lang":"ru-RU","type":"typing","grade_min":5,"grade_max":5,"tags":"unit:W-EN-G5-0028","text":"Мы учимся вместе"},{"id":"W-EN-G5-0029","lang":"ru-RU","type":"typing","grade_min":5,"grade_max":5,"tags":"unit:W-EN-G5-0029","text":"Надеемся помогать другим"},{"id":"W-EN-G5-0030","lang":"ru-RU","type":"typing","grade_min":5,"grade_max":5,"tags":"unit:W-EN-G5-0030","text":"В нашем сообществе тепло"},{"id":"W-EN-G5-0031","lang":"ru-RU","type":"typing","grade_min":5,"grade_max":5,"tags":"unit:W-EN-G5-0031","text":"Каждый заслуживает уважения"},{"id":"W-EN-G5-0032","lang":"ru-RU","type":"typing","grade_min":5,"grade_max":5,"tags":"unit:W-EN-G5-0032","text":"Давайте вместе участвовать в мероприятиях нашего сообщества"},{"id":"W-EN-G5-0033","lang":"ru-RU","type":"typing","grade_min":5,"grade_max":5,"tags":"unit:W-EN-G5-0033","text":"Нашему сообществу нужны волонтёры"},{"id":"W-EN-G5-0034","lang":"ru-RU","type":"typing","grade_min":5,"grade_max":5,"tags":"unit:W-EN-G5-0034","text":"Делиться — это важно"},{"id":"W-EN-G5-0035","lang":"ru-RU","type":"typing","grade_min":5,"grade_max":5,"tags":"unit:W-EN-G5-0035","text":"Наша цель — улучшать жизнь"},{"id":"W-EN-G5-0036","lang":"ru-RU","type":"typing","grade_min":5,"grade_max":5,"tags":"unit:W-EN-G5-0036","text":"Добро пожаловать всем"},{"id":"W-EN-G5-0037","lang":"ru-RU","type":"typing","grade_min":5,"grade_max":5,"tags":"unit:W-EN-G5-0037","text":"Работа — это сила команды"},{"id":"W-EN-G5-0038","lang":"ru-RU","type":"typing","grade_min":5,"grade_max":5,"tags":"unit:W-EN-G5-0038","text":"Вода — источник жизни"},{"id":"W-EN-G5-0039","lang":"ru-RU","type":"typing","grade_min":5,"grade_max":5,"tags":"unit:W-EN-G5-0039","text":"Мы работаем вместе"},{"id":"W-EN-G5-0040","lang":"ru-RU","type":"typing","grade_min":5,"grade_max":5,"tags":"unit:W-EN-G5-0040","text":"Тёплая улыбка"},{"id":"W-EN-G5-0041","lang":"ru-RU","type":"typing","grade_min":5,"grade_max":5,"tags":"unit:W-EN-G5-0041","text":"Обеспечение безопасности сообщества"},{"id":"W-EN-G5-0042","lang":"ru-RU","type":"typing","grade_min":5,"grade_max":5,"tags":"unit:W-EN-G5-0042","text":"Самоотверженная преданность"},{"id":"W-EN-G5-0043","lang":"ru-RU","type":"typing","grade_min":5,"grade_max":5,"tags":"unit:W-EN-G5-0043","text":"Семя надежды"},{"id":"W-EN-G5-0044","lang":"ru-RU","type":"typing","grade_min":5,"grade_max":5,"tags":"unit:W-EN-G5-0044","text":"Думать о других"},{"id":"W-EN-G5-0045","lang":"ru-RU","type":"typing","grade_min":5,"grade_max":5,"tags":"unit:W-EN-G5-0045","text":"Поддерживать дружеские отношения"},{"id":"W-EN-G6-0001","lang":"ru-RU","type":"typing","grade_min":6,"grade_max":6,"tags":"unit:W-EN-G6-0001","text":"Варёное яйцо"},{"id":"W-EN-G6-0002","lang":"ru-RU","type":"typing","grade_min":6,"grade_max":6,"tags":"unit:W-EN-G6-0002","text":"Арбуз — летний фрукт"},{"id":"W-EN-G6-0003","lang":"ru-RU","type":"typing","grade_min":6,"grade_max":6,"tags":"unit:W-EN-G6-0003","text":"Вкусные пельмени"},{"id":"W-EN-G6-0004","lang":"ru-RU","type":"typing","grade_min":6,"grade_max":6,"tags":"unit:W-EN-G6-0004","text":"Тёплый суп"},{"id":"W-EN-G6-0005","lang":"ru-RU","type":"typing","grade_min":6,"grade_max":6,"tags":"unit:W-EN-G6-0005","text":"Хрустящая картошка фри"},{"id":"W-EN-G6-0006","lang":"ru-RU","type":"typing","grade_min":6,"grade_max":6,"tags":"unit:W-EN-G6-0006","text":"Вкус виски"},{"id":"W-EN-G6-0007","lang":"ru-RU","type":"typing","grade_min":6,"grade_max":6,"tags":"unit:W-EN-G6-0007","text":"Белый рис — основной продукт питания"},{"id":"W-EN-G6-0008","lang":"ru-RU","type":"typing","grade_min":6,"grade_max":6,"tags":"unit:W-EN-G6-0008","text":"Запах шашлыка"},{"id":"W-EN-G6-0009","lang":"ru-RU","type":"typing","grade_min":6,"grade_max":6,"tags":"unit:W-EN-G6-0009","text":"Соблазн сладостей"},{"id":"W-EN-G6-0010","lang":"ru-RU","type":"typing","grade_min":6,"grade_max":6,"tags":"unit:W-EN-G6-0010","text":"Неотразимая пицца"},{"id":"W-EN-G6-0011","lang":"ru-RU","type":"typing","grade_min":6,"grade_max":6,"tags":"unit:W-EN-G6-0011","text":"Обильный фруктовый салат"},{"id":"W-EN-G6-0012","lang":"ru-RU","type":"typing","grade_min":6,"grade_max":6,"tags":"unit:W-EN-G6-0012","text":"Пельмени"},{"id":"W-EN-G6-0013","lang":"ru-RU","type":"typing","grade_min":6,"grade_max":6,"tags":"unit:W-EN-G6-0013","text":"Арбуз очень вкусный"},{"id":"W-EN-G6-0014","lang":"ru-RU","type":"typing","grade_min":6,"grade_max":6,"tags":"unit:W-EN-G6-0014","text":"Вкусное печенье"},{"id":"W-EN-G6-0015","lang":"ru-RU","type":"typing","grade_min":6,"grade_max":6,"tags":"unit:W-EN-G6-0015","text":"Белый рис"},{"id":"W-EN-G6-0016","lang":"ru-RU","type":"typing","grade_min":6,"grade_max":6,"tags":"unit:W-EN-G6-0016","text":"Мне нравится курица в виски-соусе"},{"id":"W-EN-G6-0017","lang":"ru-RU","type":"typing","grade_min":6,"grade_max":6,"tags":"unit:W-EN-G6-0017","text":"Вкусный фруктовый салат"},{"id":"W-EN-G6-0018","lang":"ru-RU","type":"typing","grade_min":6,"grade_max":6,"tags":"unit:W-EN-G6-0018","text":"Тёплый хлеб"},{"id":"W-EN-G6-0019","lang":"ru-RU","type":"typing","grade_min":6,"grade_max":6,"tags":"unit:W-EN-G6-0019","text":"Моё любимое блюдо — жареная курица"},{"id":"W-EN-G6-0020","lang":"ru-RU","type":"typing","grade_min":6,"grade_max":6,"tags":"unit:W-EN-G6-0020","text":"Виски используется для приготовления коктейлей"},{"id":"W-EN-G6-0021","lang":"ru-RU","type":"typing","grade_min":6,"grade_max":6,"tags":"unit:W-EN-G6-0021","text":"арбуз"},{"id":"W-EN-G6-0022","lang":"ru-RU","type":"typing","grade_min":6,"grade_max":6,"tags":"unit:W-EN-G6-0022","text":"шашлык"},{"id":"W-EN-G6-0023","lang":"ru-RU","type":"typing","grade_min":6,"grade_max":6,"tags":"unit:W-EN-G6-0023","text":"вкусная еда"},{"id":"W-EN-G6-0024","lang":"ru-RU","type":"typing","grade_min":6,"grade_max":6,"tags":"unit:W-EN-G6-0024","text":"виски"},{"id":"W-EN-G6-0025","lang":"ru-RU","type":"typing","grade_min":6,"grade_max":6,"tags":"unit:W-EN-G6-0025","text":"ароматная еда"},{"id":"W-EN-G6-0026","lang":"ru-RU","type":"typing","grade_min":6,"grade_max":6,"tags":"unit:W-EN-G6-0026","text":"отварные овощи"},{"id":"W-EN-G6-0027","lang":"ru-RU","type":"typing","grade_min":6,"grade_max":6,"tags":"unit:W-EN-G6-0027","text":"вкусный десерт"},{"id":"W-EN-G6-0028","lang":"ru-RU","type":"typing","grade_min":6,"grade_max":6,"tags":"unit:W-EN-G6-0028","text":"аппетитное блюдо"},{"id":"W-EN-G6-0029","lang":"ru-RU","type":"typing","grade_min":6,"grade_max":6,"tags":"unit:W-EN-G6-0029","text":"Я люблю пиццу"},{"id":"W-EN-G6-0030","lang":"ru-RU","type":"typing","grade_min":6,"grade_max":6,"tags":"unit:W-EN-G6-0030","text":"путешествие"},{"id":"W-EN-G6-0031","lang":"ru-RU","type":"typing","grade_min":6,"grade_max":6,"tags":"unit:W-EN-G6-0031","text":"мир"},{"id":"W-EN-G6-0032","lang":"ru-RU","type":"typing","grade_min":6,"grade_max":6,"tags":"unit:W-EN-G6-0032","text":"весёлое путешествие"},{"id":"W-EN-G6-0033","lang":"ru-RU","type":"typing","grade_min":6,"grade_max":6,"tags":"unit:W-EN-G6-0033","text":"живописное место"},{"id":"W-EN-G6-0034","lang":"ru-RU","type":"typing","grade_min":6,"grade_max":6,"tags":"unit:W-EN-G6-0034","text":"учиться во время путешествия"},{"id":"W-EN-G6-0035","lang":"ru-RU","type":"typing","grade_min":6,"grade_max":6,"tags":"unit:W-EN-G6-0035","text":"красивый пляж"},{"id":"W-EN-G6-0036","lang":"ru-RU","type":"typing","grade_min":6,"grade_max":6,"tags":"unit:W-EN-G6-0036","text":"открывать новые культуры"},{"id":"W-EN-G6-0037","lang":"ru-RU","type":"typing","grade_min":6,"grade_max":6,"tags":"unit:W-EN-G6-0037","text":"радости путешествий"},{"id":"W-EN-G6-0038","lang":"ru-RU","type":"typing","grade_min":6,"grade_max":6,"tags":"unit:W-EN-G6-0038","text":"по всему миру"},{"id":"W-EN-G6-0039","lang":"ru-RU","type":"typing","grade_min":6,"grade_max":6,"tags":"unit:W-EN-G6-0039","text":"воспоминания о путешествиях"},{"id":"W-EN-G6-0040","lang":"ru-RU","type":"typing","grade_min":6,"grade_max":6,"tags":"unit:W-EN-G6-0040","text":"заводить друзей в пути"},{"id":"W-EN-G6-0041","lang":"ru-RU","type":"typing","grade_min":6,"grade_max":6,"tags":"unit:W-EN-G6-0041","text":"открывать новые миры"},{"id":"W-EN-G6-0042","lang":"ru-RU","type":"typing","grade_min":6,"grade_max":6,"tags":"unit:W-EN-G6-0042","text":"прекрасные воспоминания"},{"id":"W-EN-G6-0043","lang":"ru-RU","type":"typing","grade_min":6,"grade_max":6,"tags":"unit:W-EN-G6-0043","text":"по мере смены пейзажей"},{"id":"W-EN-G6-0044","lang":"ru-RU","type":"typing","grade_min":6,"grade_max":6,"tags":"unit:W-EN-G6-0044","text":"путешествовать вместе с друзьями"},{"id":"X-EN-G1-0001","lang":"ru-RU","type":"typing","grade_min":1,"grade_max":1,"tags":"unit:X-EN-G1-0001","text":"сова"},{"id":"X-EN-G1-0001","lang":"ru-RU","type":"typing","grade_min":1,"grade_max":1,"tags":"unit:X-EN-G1-0001","text":"ручей"},{"id":"X-EN-G1-0002","lang":"ru-RU","type":"typing","grade_min":1,"grade_max":1,"tags":"unit:X-EN-G1-0002","text":"поросёнок"},{"id":"X-EN-G1-0002","lang":"ru-RU","type":"typing","grade_min":1,"grade_max":1,"tags":"unit:X-EN-G1-0002","text":"слонёнок"},{"id":"X-EN-G1-0003","lang":"ru-RU","type":"typing","grade_min":1,"grade_max":1,"tags":"unit:X-EN-G1-0003","text":"слон"},{"id":"X-EN-G1-0003","lang":"ru-RU","type":"typing","grade_min":1,"grade_max":1,"tags":"unit:X-EN-G1-0003","text":"Звёзды мерцают в ночном небе"},{"id":"X-EN-G1-0004","lang":"ru-RU","type":"typing","grade_min":1,"grade_max":1,"tags":"unit:X-EN-G1-0004","text":"акула"},{"id":"X-EN-G1-0004","lang":"ru-RU","type":"typing","grade_min":1,"grade_max":1,"tags":"unit:X-EN-G1-0004","text":"маленькая снежинка"},{"id":"X-EN-G1-0005","lang":"ru-RU","type":"typing","grade_min":1,"grade_max":1,"tags":"unit:X-EN-G1-0005","text":"тихий кролик"},{"id":"X-EN-G1-0005","lang":"ru-RU","type":"typing","grade_min":1,"grade_max":1,"tags":"unit:X-EN-G1-0005","text":"маленькое насекомое"},{"id":"X-EN-G1-0006","lang":"ru-RU","type":"typing","grade_min":1,"grade_max":1,"tags":"unit:X-EN-G1-0006","text":"милый котик"},{"id":"X-EN-G1-0006","lang":"ru-RU","type":"typing","grade_min":1,"grade_max":1,"tags":"unit:X-EN-G1-0006","text":"Ручей течёт по долине"},{"id":"X-EN-G1-0007","lang":"ru-RU","type":"typing","grade_min":1,"grade_max":1,"tags":"unit:X-EN-G1-0007","text":"игривая собачка"},{"id":"X-EN-G1-0007","lang":"ru-RU","type":"typing","grade_min":1,"grade_max":1,"tags":"unit:X-EN-G1-0007","text":"с особой осторожностью"},{"id":"X-EN-G1-0008","lang":"ru-RU","type":"typing","grade_min":1,"grade_max":1,"tags":"unit:X-EN-G1-0008","text":"красивый павлин"},{"id":"X-EN-G1-0008","lang":"ru-RU","type":"typing","grade_min":1,"grade_max":1,"tags":"unit:X-EN-G1-0008","text":"Маленькая звёздочка мерцает"},{"id":"X-EN-G1-0009","lang":"ru-RU","type":"typing","grade_min":1,"grade_max":1,"tags":"unit:X-EN-G1-0009","text":"аргентинская лошадь"},{"id":"X-EN-G1-0009","lang":"ru-RU","type":"typing","grade_min":1,"grade_max":1,"tags":"unit:X-EN-G1-0009","text":"Медвежонок под деревом"},{"id":"X-EN-G1-0010","lang":"ru-RU","type":"typing","grade_min":1,"grade_max":1,"tags":"unit:X-EN-G1-0010","text":"утёнок"},{"id":"X-EN-G1-0010","lang":"ru-RU","type":"typing","grade_min":1,"grade_max":1,"tags":"unit:X-EN-G1-0010","text":"Маленькая рыбка плывёт в воде"},{"id":"X-EN-G1-0011","lang":"ru-RU","type":"typing","grade_min":1,"grade_max":1,"tags":"unit:X-EN-G1-0011","text":"спокойный дельфин"},{"id":"X-EN-G1-0011","lang":"ru-RU","type":"typing","grade_min":1,"grade_max":1,"tags":"unit:X-EN-G1-0011","text":"маленькая фея"},{"id":"X-EN-G1-0012","lang":"ru-RU","type":"typing","grade_min":1,"grade_max":1,"tags":"unit:X-EN-G1-0012","text":"милый хомячок"},{"id":"X-EN-G1-0012","lang":"ru-RU","type":"typing","grade_min":1,"grade_max":1,"tags":"unit:X-EN-G1-0012","text":"звёздочка"},{"id":"X-EN-G1-0013","lang":"ru-RU","type":"typing","grade_min":1,"grade_max":1,"tags":"unit:X-EN-G1-0013","text":"аляскинский маламут"},{"id":"X-EN-G1-0013","lang":"ru-RU","type":"typing","grade_min":1,"grade_max":1,"tags":"unit:X-EN-G1-0013","text":"Ручей течёт"},{"id":"X-EN-G1-0014","lang":"ru-RU","type":"typing","grade_min":1,"grade_max":1,"tags":"unit:X-EN-G1-0014","text":"Белочка"},{"id":"X-EN-G1-0014","lang":"ru-RU","type":"typing","grade_min":1,"grade_max":1,"tags":"unit:X-EN-G1-0014","text":"Слонёнок идёт по лесу"},{"id":"X-EN-G1-0015","lang":"ru-RU","type":"typing","grade_min":1,"grade_max":1,"tags":"unit:X-EN-G1-0015","text":"Аргентинская кошка"},{"id":"X-EN-G1-0015","lang":"ru-RU","type":"typing","grade_min":1,"grade_max":1,"tags":"unit:X-EN-G1-0015","text":"Звёздочка мерцает"},{"id":"X-EN-G1-0016","lang":"ru-RU","type":"typing","grade_min":1,"grade_max":1,"tags":"unit:X-EN-G1-0016","text":"Тихая ящерица"},{"id":"X-EN-G1-0016","lang":"ru-RU","type":"typing","grade_min":1,"grade_max":1,"tags":"unit:X-EN-G1-0016","text":"Снежинка падает на землю"},{"id":"X-EN-G1-0017","lang":"ru-RU","type":"typing","grade_min":1,"grade_max":1,"tags":"unit:X-EN-G1-0017","text":"Ягнёнок"},{"id":"X-EN-G1-0017","lang":"ru-RU","type":"typing","grade_min":1,"grade_max":1,"tags":"unit:X-EN-G1-0017","text":"Маленькое насекомое ползает по траве."},{"id":"X-EN-G1-0018","lang":"ru-RU","type":"typing","grade_min":1,"grade_max":1,"tags":"unit:X-EN-G1-0018","text":"Озорная обезьянка."},{"id":"X-EN-G1-0018","lang":"ru-RU","type":"typing","grade_min":1,"grade_max":1,"tags":"unit:X-EN-G1-0018","text":"Вода в ручье кристально чистая, до дна видно."},{"id":"X-EN-G1-0019","lang":"ru-RU","type":"typing","grade_min":1,"grade_max":1,"tags":"unit:X-EN-G1-0019","text":"Спокойная рыба."},{"id":"X-EN-G1-0020","lang":"ru-RU","type":"typing","grade_min":1,"grade_max":1,"tags":"unit:X-EN-G1-0020","text":"Милый кролик."},{"id":"X-EN-G1-0021","lang":"ru-RU","type":"typing","grade_min":1,"grade_max":1,"tags":"unit:X-EN-G1-0021","text":"Аляскинский волк."},{"id":"X-EN-G1-0022","lang":"ru-RU","type":"typing","grade_min":1,"grade_max":1,"tags":"unit:X-EN-G1-0022","text":"Лягушонок."},{"id":"X-EN-G1-0023","lang":"ru-RU","type":"typing","grade_min":1,"grade_max":1,"tags":"unit:X-EN-G1-0023","text":"Тихая черепаха."},{"id":"X-EN-G1-0024","lang":"ru-RU","type":"typing","grade_min":1,"grade_max":1,"tags":"unit:X-EN-G1-0024","text":"Миленькая собачка."},{"id":"X-EN-G1-0025","lang":"ru-RU","type":"typing","grade_min":1,"grade_max":1,"tags":"unit:X-EN-G1-0025","text":"Аргентинская утка."},{"id":"X-EN-G1-0026","lang":"ru-RU","type":"typing","grade_min":1,"grade_max":1,"tags":"unit:X-EN-G1-0026","text":"Маленький тигрёнок."},{"id":"X-EN-G1-0027","lang":"ru-RU","type":"typing","grade_min":1,"grade_max":1,"tags":"unit:X-EN-G1-0027","text":"Тихий котик."},{"id":"X-EN-G1-0028","lang":"ru-RU","type":"typing","grade_min":1,"grade_max":1,"tags":"unit:X-EN-G1-0028","text":"Энергичная лошадка."},{"id":"X-EN-G1-0029","lang":"ru-RU","type":"typing","grade_min":1,"grade_max":1,"tags":"unit:X-EN-G1-0029","text":"Красивая бабочка."},{"id":"X-EN-G1-0030","lang":"ru-RU","type":"typing","grade_min":1,"grade_max":1,"tags":"unit:X-EN-G1-0030","text":"Спокойный лев."},{"id":"X-EN-G1-0031","lang":"ru-RU","type":"typing","grade_min":1,"grade_max":1,"tags":"unit:X-EN-G1-0031","text":"Милая совушка."},{"id":"X-EN-G1-0032","lang":"ru-RU","type":"typing","grade_min":1,"grade_max":1,"tags":"unit:X-EN-G1-0032","text":"Аргентинский кролик."},{"id":"X-EN-G1-0033","lang":"ru-RU","type":"typing","grade_min":1,"grade_max":1,"tags":"unit:X-EN-G1-0033","text":"Маленький ёжик."},{"id":"X-EN-G1-0034","lang":"ru-RU","type":"typing","grade_min":1,"grade_max":1,"tags":"unit:X-EN-G1-0034","text":"Тихая мышка."},{"id":"X-EN-G1-0035","lang":"ru-RU","type":"typing","grade_min":1,"grade_max":1,"tags":"unit:X-EN-G1-0035","text":"Бодрая акула."},{"id":"X-EN-G1-0036","lang":"ru-RU","type":"typing","grade_min":1,"grade_max":1,"tags":"unit:X-EN-G1-0036","text":"Милый дельфин."},{"id":"X-EN-G1-0037","lang":"ru-RU","type":"typing","grade_min":1,"grade_max":1,"tags":"unit:X-EN-G1-0037","text":"Маленький зайчик."},{"id":"X-EN-G1-0038","lang":"ru-RU","type":"typing","grade_min":1,"grade_max":1,"tags":"unit:X-EN-G1-0038","text":"Щенок."},{"id":"X-EN-G1-0039","lang":"ru-RU","type":"typing","grade_min":1,"grade_max":1,"tags":"unit:X-EN-G1-0039","text":"Котёнок."},{"id":"X-EN-G1-0040","lang":"ru-RU","type":"typing","grade_min":1,"grade_max":1,"tags":"unit:X-EN-G1-0040","text":"Птичка."},{"id":"X-EN-G1-0041","lang":"ru-RU","type":"typing","grade_min":1,"grade_max":1,"tags":"unit:X-EN-G1-0041","text":"лошадка"},{"id":"X-EN-G1-0042","lang":"ru-RU","type":"typing","grade_min":1,"grade_max":1,"tags":"unit:X-EN-G1-0042","text":"ягнёнок"},{"id":"X-EN-G1-0043","lang":"ru-RU","type":"typing","grade_min":1,"grade_max":1,"tags":"unit:X-EN-G1-0043","text":"жучок"},{"id":"X-EN-G1-0044","lang":"ru-RU","type":"typing","grade_min":1,"grade_max":1,"tags":"unit:X-EN-G1-0044","text":"рыбка"},{"id":"X-EN-G1-0045","lang":"ru-RU","type":"typing","grade_min":1,"grade_max":1,"tags":"unit:X-EN-G1-0045","text":"милые животные"},{"id":"X-EN-G1-0046","lang":"ru-RU","type":"typing","grade_min":1,"grade_max":1,"tags":"unit:X-EN-G1-0046","text":"собачка, которая любит поесть"},{"id":"X-EN-G1-0047","lang":"ru-RU","type":"typing","grade_min":1,"grade_max":1,"tags":"unit:X-EN-G1-0047","text":"кролик, который любит играть"},{"id":"X-EN-G1-0048","lang":"ru-RU","type":"typing","grade_min":1,"grade_max":1,"tags":"unit:X-EN-G1-0048","text":"лягушка, которая любит прыгать"},{"id":"X-EN-G1-0049","lang":"ru-RU","type":"typing","grade_min":1,"grade_max":1,"tags":"unit:X-EN-G1-0049","text":"птичка, которая любит щебетать"},{"id":"X-EN-G1-0050","lang":"ru-RU","type":"typing","grade_min":1,"grade_max":1,"tags":"unit:X-EN-G1-0050","text":"рыбка, которая любит плавать"},{"id":"X-EN-G1-0051","lang":"ru-RU","type":"typing","grade_min":1,"grade_max":1,"tags":"unit:X-EN-G1-0051","text":"змейка, которая любит ползать"},{"id":"X-EN-G1-0052","lang":"ru-RU","type":"typing","grade_min":1,"grade_max":1,"tags":"unit:X-EN-G1-0052","text":"бабочка, которая любит летать"},{"id":"X-EN-G1-0053","lang":"ru-RU","type":"typing","grade_min":1,"grade_max":1,"tags":"unit:X-EN-G1-0053","text":"лошадка, которая любит бегать"},{"id":"X-EN-G1-0054","lang":"ru-RU","type":"typing","grade_min":1,"grade_max":1,"tags":"unit:X-EN-G1-0054","text":"поросёнок, который любит поесть"},{"id":"X-EN-G1-0055","lang":"ru-RU","type":"typing","grade_min":1,"grade_max":1,"tags":"unit:X-EN-G1-0055","text":"кошечка, которая любит мяукать"},{"id":"X-EN-G1-0056","lang":"ru-RU","type":"typing","grade_min":1,"grade_max":1,"tags":"unit:X-EN-G1-0056","text":"спокойный дельфин"},{"id":"X-EN-G1-0057","lang":"ru-RU","type":"typing","grade_min":1,"grade_max":1,"tags":"unit:X-EN-G1-0057","text":"спокойная черепаха"},{"id":"X-EN-G1-0058","lang":"ru-RU","type":"typing","grade_min":1,"grade_max":1,"tags":"unit:X-EN-G1-0058","text":"тихий кит"},{"id":"X-EN-G1-0059","lang":"ru-RU","type":"typing","grade_min":1,"grade_max":1,"tags":"unit:X-EN-G1-0059","text":"тихая сова"},{"id":"X-EN-G1-0060","lang":"ru-RU","type":"typing","grade_min":1,"grade_max":1,"tags":"unit:X-EN-G1-0060","text":"тихая птичка"},{"id":"X-EN-G1-0061","lang":"ru-RU","type":"typing","grade_min":1,"grade_max":1,"tags":"unit:X-EN-G1-0061","text":"тихая собачка"},{"id":"X-EN-G1-0062","lang":"ru-RU","type":"typing","grade_min":1,"grade_max":1,"tags":"unit:X-EN-G1-0062","text":"тихая змейка"},{"id":"X-EN-G1-0063","lang":"ru-RU","type":"typing","grade_min":1,"grade_max":1,"tags":"unit:X-EN-G1-0063","text":"спокойная лошадка"},{"id":"X-EN-G1-0064","lang":"ru-RU","type":"typing","grade_min":1,"grade_max":1,"tags":"unit:X-EN-G1-0064","text":"спокойный поросёнок"},{"id":"X-EN-G1-0065","lang":"ru-RU","type":"typing","grade_min":1,"grade_max":1,"tags":"unit:X-EN-G1-0065","text":"дельфин в воде"},{"id":"X-EN-G1-0066","lang":"ru-RU","type":"typing","grade_min":1,"grade_max":1,"tags":"unit:X-EN-G1-0066","text":"Утёнок плавает"},{"id":"X-EN-G1-0067","lang":"ru-RU","type":"typing","grade_min":1,"grade_max":1,"tags":"unit:X-EN-G1-0067","text":"Спокойный тигр"},{"id":"X-EN-G1-0068","lang":"ru-RU","type":"typing","grade_min":1,"grade_max":1,"tags":"unit:X-EN-G1-0068","text":"Щенок играет"},{"id":"X-EN-G1-0069","lang":"ru-RU","type":"typing","grade_min":1,"grade_max":1,"tags":"unit:X-EN-G1-0069","text":"Ягнёнок жует траву"},{"id":"X-EN-G1-0070","lang":"ru-RU","type":"typing","grade_min":1,"grade_max":1,"tags":"unit:X-EN-G1-0070","text":"Парящий орёл"},{"id":"X-EN-G1-0071","lang":"ru-RU","type":"typing","grade_min":1,"grade_max":1,"tags":"unit:X-EN-G1-0071","text":"Милая выдра"},{"id":"X-EN-G1-0072","lang":"ru-RU","type":"typing","grade_min":1,"grade_max":1,"tags":"unit:X-EN-G1-0072","text":"Котёнок кувыркается"},{"id":"X-EN-G1-0073","lang":"ru-RU","type":"typing","grade_min":1,"grade_max":1,"tags":"unit:X-EN-G1-0073","text":"Тихая лягушка"},{"id":"X-EN-G1-0074","lang":"ru-RU","type":"typing","grade_min":1,"grade_max":1,"tags":"unit:X-EN-G1-0074","text":"Пони бегает"},{"id":"X-EN-G1-0075","lang":"ru-RU","type":"typing","grade_min":1,"grade_max":1,"tags":"unit:X-EN-G1-0075","text":"Птичка поёт"},{"id":"X-EN-G1-0076","lang":"ru-RU","type":"typing","grade_min":1,"grade_max":1,"tags":"unit:X-EN-G1-0076","text":"Жучок ползает"},{"id":"X-EN-G1-0077","lang":"ru-RU","type":"typing","grade_min":1,"grade_max":1,"tags":"unit:X-EN-G1-0077","text":"Милый ёжик"},{"id":"X-EN-G1-0078","lang":"ru-RU","type":"typing","grade_min":1,"grade_max":1,"tags":"unit:X-EN-G1-0078","text":"Рыбка плывёт"},{"id":"X-EN-G1-0079","lang":"ru-RU","type":"typing","grade_min":1,"grade_max":1,"tags":"unit:X-EN-G1-0079","text":"Гусёнок гуляет"},{"id":"X-EN-G1-0080","lang":"ru-RU","type":"typing","grade_min":1,"grade_max":1,"tags":"unit:X-EN-G1-0080","text":"Мышонок ищет еду"},{"id":"X-EN-G1-0081","lang":"ru-RU","type":"typing","grade_min":1,"grade_max":1,"tags":"unit:X-EN-G1-0081","text":"Весёлая белка"},{"id":"X-EN-G1-0082","lang":"ru-RU","type":"typing","grade_min":1,"grade_max":1,"tags":"unit:X-EN-G1-0082","text":"Маленькая акула плавает в море"},{"id":"X-EN-G1-0083","lang":"ru-RU","type":"typing","grade_min":1,"grade_max":1,"tags":"unit:X-EN-G1-0083","text":"Кролик прыгает"},{"id":"X-EN-G1-0084","lang":"ru-RU","type":"typing","grade_min":1,"grade_max":1,"tags":"unit:X-EN-G1-0084","text":"Учебник"},{"id":"X-EN-G1-0085","lang":"ru-RU","type":"typing","grade_min":1,"grade_max":1,"tags":"unit:X-EN-G1-0085","text":"Карандаш"},{"id":"X-EN-G1-0086","lang":"ru-RU","type":"typing","grade_min":1,"grade_max":1,"tags":"unit:X-EN-G1-0086","text":"Урок"},{"id":"X-EN-G1-0087","lang":"ru-RU","type":"typing","grade_min":1,"grade_max":1,"tags":"unit:X-EN-G1-0087","text":"Учимся с удовольствием"},{"id":"X-EN-G1-0088","lang":"ru-RU","type":"typing","grade_min":1,"grade_max":1,"tags":"unit:X-EN-G1-0088","text":"Урок природоведения"},{"id":"X-EN-G1-0089","lang":"ru-RU","type":"typing","grade_min":1,"grade_max":1,"tags":"unit:X-EN-G1-0089","text":"Карточная игра"},{"id":"X-EN-G1-0090","lang":"ru-RU","type":"typing","grade_min":1,"grade_max":1,"tags":"unit:X-EN-G1-0090","text":"Читать книгу"},{"id":"X-EN-G1-0091","lang":"ru-RU","type":"typing","grade_min":1,"grade_max":1,"tags":"unit:X-EN-G1-0091","text":"Внеурочная деятельность"},{"id":"X-EN-G1-0092","lang":"ru-RU","type":"typing","grade_min":1,"grade_max":1,"tags":"unit:X-EN-G1-0092","text":"Весёлый друг"},{"id":"X-EN-G1-0093","lang":"ru-RU","type":"typing","grade_min":1,"grade_max":1,"tags":"unit:X-EN-G1-0093","text":"Подготовка к тестам"},{"id":"X-EN-G1-0094","lang":"ru-RU","type":"typing","grade_min":1,"grade_max":1,"tags":"unit:X-EN-G1-0094","text":"Расписание уроков"},{"id":"X-EN-G1-0095","lang":"ru-RU","type":"typing","grade_min":1,"grade_max":1,"tags":"unit:X-EN-G1-0095","text":"Пустой лист бумаги"},{"id":"X-EN-G1-0096","lang":"ru-RU","type":"typing","grade_min":1,"grade_max":1,"tags":"unit:X-EN-G1-0096","text":"Милый учитель"},{"id":"X-EN-G1-0097","lang":"ru-RU","type":"typing","grade_min":1,"grade_max":1,"tags":"unit:X-EN-G1-0097","text":"Дополнительные занятия после уроков"},{"id":"X-EN-G1-0098","lang":"ru-RU","type":"typing","grade_min":1,"grade_max":1,"tags":"unit:X-EN-G1-0098","text":"Счастливые моменты"},{"id":"X-EN-G1-0099","lang":"ru-RU","type":"typing","grade_min":1,"grade_max":1,"tags":"unit:X-EN-G1-0099","text":"Бланк контрольной работы"},{"id":"X-EN-G1-0100","lang":"ru-RU","type":"typing","grade_min":1,"grade_max":1,"tags":"unit:X-EN-G1-0100","text":"Упражнения на устный счёт"},{"id":"X-EN-G1-0101","lang":"ru-RU","type":"typing","grade_min":1,"grade_max":1,"tags":"unit:X-EN-G1-0101","text":"Рассказы по картинке"},{"id":"X-EN-G1-0102","lang":"ru-RU","type":"typing","grade_min":1,"grade_max":1,"tags":"unit:X-EN-G1-0102","text":"Научный эксперимент"},{"id":"X-EN-G1-0103","lang":"ru-RU","type":"typing","grade_min":1,"grade_max":1,"tags":"unit:X-EN-G1-0103","text":"Классное обсуждение"},{"id":"X-EN-G1-0104","lang":"ru-RU","type":"typing","grade_min":1,"grade_max":1,"tags":"unit:X-EN-G1-0104","text":"Открытый ум"},{"id":"X-EN-G1-0105","lang":"ru-RU","type":"typing","grade_min":1,"grade_max":1,"tags":"unit:X-EN-G1-0105","text":"Приёмы для успешной сдачи тестов"},{"id":"X-EN-G1-0106","lang":"ru-RU","type":"typing","grade_min":1,"grade_max":1,"tags":"unit:X-EN-G1-0106","text":"Конспект урока"},{"id":"X-EN-G1-0107","lang":"ru-RU","type":"typing","grade_min":1,"grade_max":1,"tags":"unit:X-EN-G1-0107","text":"Вкусный обед"},{"id":"X-EN-G1-0108","lang":"ru-RU","type":"typing","grade_min":1,"grade_max":1,"tags":"unit:X-EN-G1-0108","text":"Радостная школа"},{"id":"X-EN-G1-0109","lang":"ru-RU","type":"typing","grade_min":1,"grade_max":1,"tags":"unit:X-EN-G1-0109","text":"Размышление над задачей"},{"id":"X-EN-G1-0110","lang":"ru-RU","type":"typing","grade_min":1,"grade_max":1,"tags":"unit:X-EN-G1-0110","text":"Обложка учебника"},{"id":"X-EN-G1-0111","lang":"ru-RU","type":"typing","grade_min":1,"grade_max":1,"tags":"unit:X-EN-G1-0111","text":"Свежий воздух"},{"id":"X-EN-G1-0112","lang":"ru-RU","type":"typing","grade_min":1,"grade_max":1,"tags":"unit:X-EN-G1-0112","text":"Весёлый смех"},{"id":"X-EN-G1-0113","lang":"ru-RU","type":"typing","grade_min":1,"grade_max":1,"tags":"unit:X-EN-G1-0113","text":"Научные знания"},{"id":"X-EN-G1-0114","lang":"ru-RU","type":"typing","grade_min":1,"grade_max":1,"tags":"unit:X-EN-G1-0114","text":"Занятия в классе"},{"id":"X-EN-G1-0115","lang":"ru-RU","type":"typing","grade_min":1,"grade_max":1,"tags":"unit:X-EN-G1-0115","text":"Результаты теста"},{"id":"X-EN-G1-0116","lang":"ru-RU","type":"typing","grade_min":1,"grade_max":1,"tags":"unit:X-EN-G1-0116","text":"радостные способы учёбы"},{"id":"X-EN-G1-0117","lang":"ru-RU","type":"typing","grade_min":1,"grade_max":1,"tags":"unit:X-EN-G1-0117","text":"внеклассное чтение"},{"id":"X-EN-G1-0118","lang":"ru-RU","type":"typing","grade_min":1,"grade_max":1,"tags":"unit:X-EN-G1-0118","text":"милый одноклассник"},{"id":"X-EN-G1-0119","lang":"ru-RU","type":"typing","grade_min":1,"grade_max":1,"tags":"unit:X-EN-G1-0119","text":"весёлые воспоминания"},{"id":"X-EN-G1-0120","lang":"ru-RU","type":"typing","grade_min":1,"grade_max":1,"tags":"unit:X-EN-G1-0120","text":"время теста"},{"id":"X-EN-G1-0121","lang":"ru-RU","type":"typing","grade_min":1,"grade_max":1,"tags":"unit:X-EN-G1-0121","text":"класс"},{"id":"X-EN-G1-0122","lang":"ru-RU","type":"typing","grade_min":1,"grade_max":1,"tags":"unit:X-EN-G1-0122","text":"знания"},{"id":"X-EN-G1-0123","lang":"ru-RU","type":"typing","grade_min":1,"grade_max":1,"tags":"unit:X-EN-G1-0123","text":"радость"},{"id":"X-EN-G1-0124","lang":"ru-RU","type":"typing","grade_min":1,"grade_max":1,"tags":"unit:X-EN-G1-0124","text":"учебный курс"},{"id":"X-EN-G1-0125","lang":"ru-RU","type":"typing","grade_min":1,"grade_max":1,"tags":"unit:X-EN-G1-0125","text":"естествознание"},{"id":"X-EN-G1-0126","lang":"ru-RU","type":"typing","grade_min":1,"grade_max":1,"tags":"unit:X-EN-G1-0126","text":"тест"},{"id":"X-EN-G1-0127","lang":"ru-RU","type":"typing","grade_min":1,"grade_max":1,"tags":"unit:X-EN-G1-0127","text":"карточка"},{"id":"X-EN-G1-0128","lang":"ru-RU","type":"typing","grade_min":1,"grade_max":1,"tags":"unit:X-EN-G1-0128","text":"пространство"},{"id":"X-EN-G1-0129","lang":"ru-RU","type":"typing","grade_min":1,"grade_max":1,"tags":"unit:X-EN-G1-0129","text":"весёлый"},{"id":"X-EN-G1-0130","lang":"ru-RU","type":"typing","grade_min":1,"grade_max":1,"tags":"unit:X-EN-G1-0130","text":"устная речь"},{"id":"X-EN-G1-0131","lang":"ru-RU","type":"typing","grade_min":1,"grade_max":1,"tags":"unit:X-EN-G1-0131","text":"милый друг"},{"id":"X-EN-G1-0132","lang":"ru-RU","type":"typing","grade_min":1,"grade_max":1,"tags":"unit:X-EN-G1-0132","text":"герой мультфильма"},{"id":"X-EN-G1-0133","lang":"ru-RU","type":"typing","grade_min":1,"grade_max":1,"tags":"unit:X-EN-G1-0133","text":"открытое мышление"}],"page":3,"next":4}